obcli/__init__.py
obcli-0.0.1.dist-info/DESCRIPTION.rst
obcli-0.0.1.dist-info/METADATA
obcli-0.0.1.dist-info/RECORD
obcli-0.0.1.dist-info/WHEEL
obcli-0.0.1.dist-info/metadata.json
obcli-0.0.1.dist-info/top_level.txt
