Metadata-Version: 2.0
Name: obcli
Version: 0.0.1
Summary: Openbayes command line tool
Home-page: https://github.com/pypa/example-project
Author: openbayes
Author-email: shanchuan@signcl.com
License: UNKNOWN
Platform: UNKNOWN
Classifier: Programming Language :: Python :: 3
Classifier: Operating System :: OS Independent
